sphinx_vhdl-0.2.2.dist-info/licenses/LICENSE
sphinxvhdl/__init__.py
sphinxvhdl/autodoc.py
sphinxvhdl/vhdl.py
sphinx_vhdl-0.2.2.dist-info/METADATA
sphinx_vhdl-0.2.2.dist-info/WHEEL
sphinx_vhdl-0.2.2.dist-info/top_level.txt
sphinx_vhdl-0.2.2.dist-info/RECORD
