Metadata-Version: 2.4
Name: sphinx-vhdl
Version: 0.2.2
Summary: A Sphinx domain and autodocumenter for VHDL
Author: CESNET z.s.p.o.
Author-email: cabal@cesnet.cz
License: BSD-3-Clause
Classifier: Programming Language :: Python :: 3
Classifier: Operating System :: OS Independent
Classifier: Topic :: Documentation :: Sphinx
Classifier: Development Status :: 4 - Beta
Classifier: Environment :: Plugins
Classifier: Framework :: Sphinx :: Extension
Classifier: Intended Audience :: Developers
Classifier: License :: OSI Approved :: BSD License
Requires-Python: >=3.8
License-File: LICENSE
Requires-Dist: sphinx>=6.0
Dynamic: license-file
